leven_search/__init__.py
leven_search/config.py
leven_search/cost.py
leven_search/leven_search.py
leven_search/result.py
leven_search/state.py
leven_search/trie.py
leven_search-0.2.1.dist-info/LICENSE
leven_search-0.2.1.dist-info/METADATA
leven_search-0.2.1.dist-info/WHEEL
leven_search-0.2.1.dist-info/top_level.txt
leven_search-0.2.1.dist-info/RECORD
