Metadata-Version: 2.1
Name: leven-search
Version: 0.2.1
Summary: Fast and flexible search in a dictionary using Levenshtein distance
Author-email: Piotr Kozłowski <piotr.kozlowski@gmail.com>
License: MIT
Project-URL: Homepage, https://github.com/pkoz/leven-search
Project-URL: Repository, https://github.com/pkoz/leven-search
Keywords: levenshtein,search,fuzzy,dictionary,trie
Classifier: Intended Audience :: Developers
Classifier: Programming Language :: Python
Classifier: License :: OSI Approved :: MIT License
Classifier: Operating System :: OS Independent
Classifier: Topic :: Software Development :: Libraries :: Python Modules
Classifier: Topic :: Text Processing :: Linguistic
Classifier: Topic :: Text Processing :: General
Classifier: Topic :: Utilities
Requires-Python: >=3.8
License-File: LICENSE
Provides-Extra: tests
Requires-Dist: pytest ; extra == 'tests'
Requires-Dist: nltk ; extra == 'tests'
Requires-Dist: coverage ; extra == 'tests'
Requires-Dist: coverage-badge ; extra == 'tests'
